{
  "created_at": "2026-03-18T21:06:23.629Z",
  "trigger": "manual",
  "registrations": [
    {
      "id": "98d3439b-e7c3-485d-9712-36ba85c53d92",
      "registration_code": "CGN-HWNF76",
      "event_slug": "squid-game",
      "team_name": "Aditya",
      "college_name": "DVVCOE",
      "department_name": "CE",
      "year_of_study": "TE",
      "contact_name": "Aditya",
      "contact_email": "gagareaditya32@gmail.com",
      "contact_phone": "7558394479",
      "payment_method": "upi",
      "payment_reference": "0000000000000",
      "total_amount": 50,
      "status": "verified",
      "review_note": null,
      "attendance_status": "checked-in",
      "created_at": "2026-03-18T20:47:47.293Z",
      "updated_at": "2026-03-18T21:04:09.302Z",
      "event_name": "Squid Game",
      "date_label": "08 Apr 2026",
      "time_label": "09:00 AM",
      "venue": "NASA Point",
      "participants": [
        {
          "fullName": "Aditya Gagare",
          "email": "gagareaditya32@gmail.com",
          "phone": "7558394479",
          "isLead": true
        }
      ]
    },
    {
      "id": "7e87f2a7-ac01-468b-87b9-bf6215985526",
      "registration_code": "CGN-PPUPWQ",
      "event_slug": "squid-game",
      "team_name": "Sanket",
      "college_name": "DVVPCOE",
      "department_name": "CE",
      "year_of_study": "TE",
      "contact_name": "Sanket",
      "contact_email": "sanketmeghale@gmail.com",
      "contact_phone": "9356776307",
      "payment_method": "upi",
      "payment_reference": "12345678",
      "total_amount": 50,
      "status": "verified",
      "review_note": null,
      "attendance_status": "registered",
      "created_at": "2026-03-18T19:34:40.116Z",
      "updated_at": "2026-03-18T19:35:32.826Z",
      "event_name": "Squid Game",
      "date_label": "08 Apr 2026",
      "time_label": "09:00 AM",
      "venue": "NASA Point",
      "participants": [
        {
          "fullName": "Sanket",
          "email": "sanketmeghale@gmail.com",
          "phone": "9356776307",
          "isLead": true
        }
      ]
    },
    {
      "id": "728bc1e2-2fb1-49f9-a514-92526e72da05",
      "registration_code": "CGN-26HNY1",
      "event_slug": "squid-game",
      "team_name": "Aditya Gagare",
      "college_name": "DVVPCOE",
      "department_name": "CE",
      "year_of_study": "TE",
      "contact_name": "Aditya Gagare",
      "contact_email": "sanketmeghale@gmail.com",
      "contact_phone": "7558394479",
      "payment_method": "upi",
      "payment_reference": "12345678",
      "total_amount": 50,
      "status": "verified",
      "review_note": null,
      "attendance_status": "registered",
      "created_at": "2026-03-18T18:39:43.694Z",
      "updated_at": "2026-03-18T18:41:57.869Z",
      "event_name": "Squid Game",
      "date_label": "08 Apr 2026",
      "time_label": "09:00 AM",
      "venue": "NASA Point",
      "participants": [
        {
          "fullName": "Aditya Gagare",
          "email": "sanketmeghale@gmail.com",
          "phone": "7558394479",
          "isLead": true
        }
      ]
    },
    {
      "id": "c6514037-76cf-446e-bee7-f513e0a6be85",
      "registration_code": "CGN-VOXO88",
      "event_slug": "squid-game",
      "team_name": "Sanket",
      "college_name": "DVVPCOE",
      "department_name": "CE",
      "year_of_study": "3",
      "contact_name": "Sanket",
      "contact_email": "sanketmeghale@gmail.com",
      "contact_phone": "9356776307",
      "payment_method": "upi",
      "payment_reference": "123456789",
      "total_amount": 50,
      "status": "verified",
      "review_note": null,
      "attendance_status": "registered",
      "created_at": "2026-03-18T16:44:40.367Z",
      "updated_at": "2026-03-18T18:42:08.973Z",
      "event_name": "Squid Game",
      "date_label": "08 Apr 2026",
      "time_label": "09:00 AM",
      "venue": "NASA Point",
      "participants": [
        {
          "fullName": "Sanket  Meghale",
          "email": "sanketmeghale@gmail.com",
          "phone": "9356776307",
          "isLead": true
        }
      ]
    },
    {
      "id": "6a073bc8-fcf7-4aa2-979e-c25562b00e02",
      "registration_code": "CGN-NPREBA",
      "event_slug": "squid-game",
      "team_name": "Sanket",
      "college_name": "DVVPCOE",
      "department_name": "Computer",
      "year_of_study": "3",
      "contact_name": "Sanket",
      "contact_email": "sanketmeghale@gmail.com",
      "contact_phone": "9356776307",
      "payment_method": "upi",
      "payment_reference": null,
      "total_amount": 50,
      "status": "verified",
      "review_note": null,
      "attendance_status": "registered",
      "created_at": "2026-03-18T14:14:48.444Z",
      "updated_at": "2026-03-18T18:42:13.252Z",
      "event_name": "Squid Game",
      "date_label": "08 Apr 2026",
      "time_label": "09:00 AM",
      "venue": "NASA Point",
      "participants": [
        {
          "fullName": "Sanket",
          "email": "sanketmeghale@gmail.com",
          "phone": "9356776307",
          "isLead": true
        }
      ]
    },
    {
      "id": "3c2d7ffc-b01b-4cfc-8eca-778d9c37dda8",
      "registration_code": "CGN-4RQ4NS",
      "event_slug": "squid-game",
      "team_name": "Aarav Shah",
      "college_name": "DVVPOE",
      "department_name": "Computer Engineering",
      "year_of_study": "Second Year",
      "contact_name": "Aarav Shah",
      "contact_email": "aarav@example.com",
      "contact_phone": "9876543210",
      "payment_method": "upi",
      "payment_reference": "UPI12345",
      "total_amount": 50,
      "status": "verified",
      "review_note": null,
      "attendance_status": "registered",
      "created_at": "2026-03-18T13:45:17.328Z",
      "updated_at": "2026-03-18T19:05:15.700Z",
      "event_name": "Squid Game",
      "date_label": "08 Apr 2026",
      "time_label": "09:00 AM",
      "venue": "NASA Point",
      "participants": [
        {
          "fullName": "Aarav Shah",
          "email": "aarav@example.com",
          "phone": "9876543210",
          "isLead": true
        }
      ]
    }
  ],
  "events": [
    {
      "id": 1,
      "slug": "tech-kbc",
      "name": "TechKBC",
      "category": "Technical",
      "date_label": "07 Apr 2026",
      "time_label": "02:00 PM",
      "venue": "CE Department",
      "description": "A fast-paced technical quiz for students who enjoy sharp thinking, buzzer pressure, and team strategy.",
      "prize": "INR 10,000",
      "registration_fee": 100,
      "min_members": 2,
      "max_members": 2,
      "max_slots": 60,
      "is_team_event": true,
      "is_active": true,
      "created_at": "2026-03-18T13:42:39.087Z",
      "updated_at": "2026-03-18T20:33:17.743Z",
      "registration_fee_label": "INR 100 per team",
      "poster_path": "/images/techkbc.jpg",
      "payment_upi": "sahilbhatti292005@okaxis",
      "payment_payee": "Sahil Bhatti",
      "registrations_count": 0,
      "waitlist_count": 0
    },
    {
      "id": 2,
      "slug": "bgmi-esports",
      "name": "Ranbhoomi (BGMI)",
      "category": "Gaming",
      "date_label": "07 Apr 2026",
      "time_label": "10:30 AM",
      "venue": "Seminar Hall",
      "description": "Squad-based battleground tournament with coordinated team entry and manual verification support.",
      "prize": "INR 5,000",
      "registration_fee": 250,
      "min_members": 4,
      "max_members": 4,
      "max_slots": 25,
      "is_team_event": true,
      "is_active": true,
      "created_at": "2026-03-18T13:42:39.115Z",
      "updated_at": "2026-03-18T20:33:17.755Z",
      "registration_fee_label": "INR 250 per squad",
      "poster_path": "/images/bgmi.jpg",
      "payment_upi": "kawadeakshay23@okaxis",
      "payment_payee": "Akshay Kawade",
      "registrations_count": 0,
      "waitlist_count": 0
    },
    {
      "id": 3,
      "slug": "ff-esports",
      "name": "Ranbhoomi (Free Fire)",
      "category": "Gaming",
      "date_label": "07 Apr 2026",
      "time_label": "10:30 AM",
      "venue": "Seminar Hall",
      "description": "Mobile survival esports event with fixed-squad registration and export-ready participant records.",
      "prize": "INR 5,000",
      "registration_fee": 250,
      "min_members": 4,
      "max_members": 4,
      "max_slots": 25,
      "is_team_event": true,
      "is_active": true,
      "created_at": "2026-03-18T13:42:39.124Z",
      "updated_at": "2026-03-18T20:33:17.759Z",
      "registration_fee_label": "INR 250 per squad",
      "poster_path": "/images/freefire.jpg",
      "payment_upi": "kawadeakshay23@okaxis",
      "payment_payee": "Akshay Kawade",
      "registrations_count": 0,
      "waitlist_count": 0
    },
    {
      "id": 4,
      "slug": "squid-game",
      "name": "Squid Game",
      "category": "Fun",
      "date_label": "08 Apr 2026",
      "time_label": "09:00 AM",
      "venue": "NASA Point",
      "description": "A solo fun event with high participant volume, built for quick on-site filtering and export.",
      "prize": "INR 7,000",
      "registration_fee": 50,
      "min_members": 1,
      "max_members": 1,
      "max_slots": 150,
      "is_team_event": false,
      "is_active": true,
      "created_at": "2026-03-18T13:42:39.130Z",
      "updated_at": "2026-03-18T20:33:17.761Z",
      "registration_fee_label": "INR 50 per person",
      "poster_path": "/images/squidgame.jpg",
      "payment_upi": "siddhideshpande11@okhdfcbank",
      "payment_payee": "Siddhi Deshpande",
      "registrations_count": 6,
      "waitlist_count": 0
    },
    {
      "id": 5,
      "slug": "rang-manch",
      "name": "Rangmanch",
      "category": "Fun",
      "date_label": "08 Apr 2026",
      "time_label": "01:00 PM",
      "venue": "Seminar Hall",
      "description": "Performance event with flexible team size, ideal for a participant portal that handles solo to group entries cleanly.",
      "prize": "INR 8,000",
      "registration_fee": 50,
      "min_members": 1,
      "max_members": 5,
      "max_slots": 35,
      "is_team_event": true,
      "is_active": true,
      "created_at": "2026-03-18T13:42:39.134Z",
      "updated_at": "2026-03-18T20:33:17.764Z",
      "registration_fee_label": "INR 50 - INR 200",
      "poster_path": "/images/rangmanch.jpg",
      "payment_upi": "chaitanyamagar418@okhdfcbank",
      "payment_payee": "Chaitanya Magar",
      "registrations_count": 0,
      "waitlist_count": 0
    },
    {
      "id": 6,
      "slug": "googler-hunt",
      "name": "Googler (Tech Treasure Hunt)",
      "category": "Technical",
      "date_label": "07 Apr 2026",
      "time_label": "10:30 AM",
      "venue": "CE Department",
      "description": "Clue-solving technical hunt that benefits from clear team validation and centralized participant data.",
      "prize": "INR 5,000",
      "registration_fee": 200,
      "min_members": 4,
      "max_members": 4,
      "max_slots": 30,
      "is_team_event": true,
      "is_active": true,
      "created_at": "2026-03-18T13:42:39.149Z",
      "updated_at": "2026-03-18T20:33:17.767Z",
      "registration_fee_label": "INR 200 per squad",
      "poster_path": "/images/techtreasurehunt.jpg",
      "payment_upi": "siddhideshpande11@okhdfcbank",
      "payment_payee": "Siddhi Deshpande",
      "registrations_count": 0,
      "waitlist_count": 0
    },
    {
      "id": 7,
      "slug": "techxcelerate",
      "name": "Techxcelerate (Project Expo)",
      "category": "Technical",
      "date_label": "08 Apr 2026",
      "time_label": "12:00 PM",
      "venue": "CE Department",
      "description": "Project showcase portal entry for prototype teams, with structured records for organizers and judges.",
      "prize": "INR 12,000",
      "registration_fee": 100,
      "min_members": 1,
      "max_members": 4,
      "max_slots": 40,
      "is_team_event": true,
      "is_active": true,
      "created_at": "2026-03-18T13:42:39.155Z",
      "updated_at": "2026-03-18T20:33:17.770Z",
      "registration_fee_label": "INR 100 - INR 200",
      "poster_path": "/images/projectexpo.jpg",
      "payment_upi": "kawadeakshay23@okaxis",
      "payment_payee": "Akshay Kawade",
      "registrations_count": 0,
      "waitlist_count": 0
    },
    {
      "id": 8,
      "slug": "utopia",
      "name": "Utopia",
      "category": "Technical",
      "date_label": "07 Apr 2026",
      "time_label": "10:30 AM",
      "venue": "CE Department",
      "description": "Flagship coding challenge with flexible squad formation and a review-friendly registration pipeline.",
      "prize": "INR 15,000",
      "registration_fee": 250,
      "min_members": 1,
      "max_members": 5,
      "max_slots": 80,
      "is_team_event": true,
      "is_active": true,
      "created_at": "2026-03-18T13:42:39.162Z",
      "updated_at": "2026-03-18T20:33:17.775Z",
      "registration_fee_label": "INR 250 per registration",
      "poster_path": "/images/hackathon.jpg",
      "payment_upi": "siddhideshpande11@okhdfcbank",
      "payment_payee": "Siddhi Deshpande",
      "registrations_count": 0,
      "waitlist_count": 0
    }
  ],
  "announcements": []
}